lib_dzne_auto_interface/Information.py
lib_dzne_auto_interface/__init__.py
lib_dzne_auto_interface/gui/HelpButton.py
lib_dzne_auto_interface/gui/Stack.py
lib_dzne_auto_interface/gui/inputs/__init__.py
lib_dzne_auto_interface/gui/inputs/_parsing_nargs.py
lib_dzne_auto_interface-0.5.1.dist-info/LICENSE.txt
lib_dzne_auto_interface-0.5.1.dist-info/METADATA
lib_dzne_auto_interface-0.5.1.dist-info/WHEEL
lib_dzne_auto_interface-0.5.1.dist-info/top_level.txt
lib_dzne_auto_interface-0.5.1.dist-info/RECORD
