Metadata-Version: 2.1
Name: lib-dzne-auto-interface
Version: 0.5.1
Summary: Libary for automatically created interfaces. 
Author-email: Johannes <johannes-programming@posteo.org>
License: Copyright © 2022 Johannes Horler
Project-URL: Download, https://pypi.org/project/lib-dzne-auto-interface/#files
Project-URL: Source, https://github.com/johannes-programming/lib_dzne_auto_interface
Classifier: License :: OSI Approved :: MIT License
Classifier: Programming Language :: Python
Classifier: Programming Language :: Python :: 3
Requires-Python: >=3.11
License-File: LICENSE.txt
